hello.py
fan_lang-0.1.1.dist-info/licenses/LICENSE
fan_lang-0.1.1.dist-info/METADATA
fan_lang-0.1.1.dist-info/WHEEL
fan_lang-0.1.1.dist-info/top_level.txt
fan_lang-0.1.1.dist-info/RECORD
