Metadata-Version: 2.4
Name: fan-lang
Version: 0.1.1
Summary: Fantom programming language
License-Expression: AFL-3.0
Requires-Python: >=3.14
License-File: LICENSE
Dynamic: license-file
